cadmium_fastapi/__init__.py
cadmium_fastapi/client.py
cadmium_fastapi/middleware.py
cadmium_fastapi_sdk-1.0.0.dist-info/licenses/LICENSE
tests/__init__.py
tests/test_client.py
tests/test_middleware.py
cadmium_fastapi_sdk-1.0.0.dist-info/METADATA
cadmium_fastapi_sdk-1.0.0.dist-info/WHEEL
cadmium_fastapi_sdk-1.0.0.dist-info/top_level.txt
cadmium_fastapi_sdk-1.0.0.dist-info/RECORD
