Metadata-Version: 2.4
Name: cadmium-fastapi-sdk
Version: 1.0.0
Summary: Cadmium SDK for capturing and sending FastAPI errors
Home-page: https://github.com/softwares-compound/cadmium-fastapi-sdk
Author: bannawandoor
Author-email: bannawandoor <connect@hasanulbanna.in>
License: MIT
Project-URL: Homepage, https://github.com/softwares-compound/cadmium-fastapi-sdk
Project-URL: Repository, https://github.com/softwares-compound/cadmium-fastapi-sdk
Project-URL: Issues, https://github.com/softwares-compound/cadmium-fastapi-sdk/issues
Keywords: fastapi,error-tracking,monitoring,cadmium
Classifier: Development Status :: 4 - Beta
Classifier: Intended Audience :: Developers
Classifier: License :: OSI Approved :: MIT License
Classifier: Operating System :: OS Independent
Classifier: Programming Language :: Python :: 3
Classifier: Programming Language :: Python :: 3.8
Classifier: Programming Language :: Python :: 3.9
Classifier: Programming Language :: Python :: 3.10
Classifier: Programming Language :: Python :: 3.11
Classifier: Framework :: FastAPI
Classifier: Topic :: Software Development :: Libraries :: Python Modules
Classifier: Topic :: System :: Monitoring
Requires-Python: >=3.8
License-File: LICENSE
Requires-Dist: fastapi>=0.68.0
Requires-Dist: httpx>=0.24.0
Requires-Dist: starlette>=0.14.0
Dynamic: author
Dynamic: home-page
Dynamic: license-file
Dynamic: requires-python
